miniopy_async/__init__.py
miniopy_async/api.py
miniopy_async/commonconfig.py
miniopy_async/credentials/__init__.py
miniopy_async/credentials/credentials.py
miniopy_async/credentials/providers.py
miniopy_async/crypto.py
miniopy_async/datatypes.py
miniopy_async/deleteobjects.py
miniopy_async/error.py
miniopy_async/helpers.py
miniopy_async/legalhold.py
miniopy_async/lifecycleconfig.py
miniopy_async/minioadmin.py
miniopy_async/notificationconfig.py
miniopy_async/objectlockconfig.py
miniopy_async/py.typed
miniopy_async/replicationconfig.py
miniopy_async/retention.py
miniopy_async/select.py
miniopy_async/signer.py
miniopy_async/sse.py
miniopy_async/sseconfig.py
miniopy_async/tagging.py
miniopy_async/time.py
miniopy_async/versioningconfig.py
miniopy_async/xml.py
miniopy_async-1.23.4.dist-info/LICENSE
miniopy_async-1.23.4.dist-info/METADATA
miniopy_async-1.23.4.dist-info/WHEEL
miniopy_async-1.23.4.dist-info/RECORD
