Metadata-Version: 2.1
Name: miniopy-async
Version: 1.23.4
Summary: Asynchronous MinIO Client SDK for Python
Home-page: https://github.com/hlf20010508/miniopy-async
License: Apache-2.0
Author: L-ING
Author-email: hlf01@icloud.com
Requires-Python: >=3.10,<4.0
Classifier: Development Status :: 5 - Production/Stable
Classifier: Intended Audience :: Developers
Classifier: License :: OSI Approved :: Apache Software License
Classifier: Natural Language :: English
Classifier: Operating System :: OS Independent
Classifier: Programming Language :: Python :: 3
Classifier: Programming Language :: Python :: 3.10
Classifier: Programming Language :: Python :: 3.11
Classifier: Programming Language :: Python :: 3.12
Classifier: Programming Language :: Python :: 3.13
Classifier: Topic :: Software Development :: Libraries :: Python Modules
Requires-Dist: aiohttp (>=3.11.14,<4.0.0)
Requires-Dist: aiohttp-retry (>=2.9.1,<3.0.0)
Requires-Dist: argon2-cffi (>=23.1.0,<24.0.0)
Requires-Dist: certifi (>=2025.1.31,<2026.0.0)
Requires-Dist: pycryptodome (>=3.22.0,<4.0.0)
Project-URL: Documentation, https://hlf20010508.github.io/miniopy-async/
Project-URL: Repository, https://github.com/hlf20010508/miniopy-async
